sort/SortTuples.py
sort/SortingAlgorithms.py
sort/__init__.py
sort_algorithms-1.0.2.dist-info/DESCRIPTION.rst
sort_algorithms-1.0.2.dist-info/METADATA
sort_algorithms-1.0.2.dist-info/RECORD
sort_algorithms-1.0.2.dist-info/WHEEL
sort_algorithms-1.0.2.dist-info/metadata.json
sort_algorithms-1.0.2.dist-info/top_level.txt
