Metadata-Version: 2.0
Name: sort-algorithms
Version: 1.0.2
Summary: Sorting algorithms written in and made for Python lists and tuples
Home-page: https://github.com/DahlitzFlorian/SortingAlgorithms
Author: Florian Dahlitz
Author-email: f2dahlitz@freenet.de
License: MIT
Keywords: sort algorithms sorting lists tuples
Platform: UNKNOWN
Classifier: Development Status :: 5 - Production/Stable
Classifier: Intended Audience :: Developers
Classifier: License :: OSI Approved :: MIT License
Classifier: Programming Language :: Python :: 3.4
Classifier: Programming Language :: Python :: 3.5
Classifier: Programming Language :: Python :: 3.6
